cqlib_algorithm/VERSION.txt
cqlib_algorithm/__init__.py
cqlib_algorithm/_version.py
cqlib_algorithm/algorithms/__init__.py
cqlib_algorithm/algorithms/qaoa/__init__.py
cqlib_algorithm/algorithms/qaoa/qaoa.py
cqlib_algorithm/algorithms/qaoa/qaoa_evaluator.py
cqlib_algorithm/algorithms/qaoa/qaoa_minimize.py
cqlib_algorithm/algorithms/qaoa/qaoa_result.py
cqlib_algorithm/ansatz/__init__.py
cqlib_algorithm/ansatz/qaoa_ansatz.py
cqlib_algorithm/execution/__init__.py
cqlib_algorithm/execution/local_runner.py
cqlib_algorithm/execution/objective.py
cqlib_algorithm/execution/platform_runner.py
cqlib_algorithm/mappings/__init__.py
cqlib_algorithm/mappings/convert.py
cqlib_algorithm/mappings/hamiltonian.py
cqlib_algorithm/mappings/qubo.py
cqlib_algorithm/optimizers/__init__.py
cqlib_algorithm/optimizers/base.py
cqlib_algorithm/optimizers/cobyla.py
cqlib_algorithm/optimizers/factory.py
cqlib_algorithm/optimizers/nelder_mead.py
cqlib_algorithm/optimizers/options.py
cqlib_algorithm/optimizers/spsa.py
cqlib_algorithm/problems/__init__.py
cqlib_algorithm/problems/maxcut.py
cqlib_algorithm/problems/tsp.py
cqlib_algorithm/problems/vrp.py
cqlib_algorithm/results/__init__.py
cqlib_algorithm/results/maxcut_decoder.py
cqlib_algorithm/results/tsp_decoder.py
cqlib_algorithm/results/utils.py
cqlib_algorithm/results/vrp_decoder.py
cqlib_algorithm/transpiler/__init__.py
cqlib_algorithm/transpiler/builders.py
cqlib_algorithm/visualization/__init__.py
cqlib_algorithm/visualization/ansatz_plot.py
cqlib_algorithm/visualization/history_plot.py
cqlib_algorithm/visualization/maxcut_plot.py
cqlib_algorithm/visualization/probability_plot.py
cqlib_algorithm/visualization/tsp_plot.py
cqlib_algorithm/visualization/vrp_plot.py
cqlib_algorithm-0.1.0.dist-info/licenses/LICENSE
cqlib_algorithm-0.1.0.dist-info/METADATA
cqlib_algorithm-0.1.0.dist-info/WHEEL
cqlib_algorithm-0.1.0.dist-info/top_level.txt
cqlib_algorithm-0.1.0.dist-info/RECORD
