Metadata-Version: 2.4
Name: cqlib-algorithm
Version: 0.1.0
Summary: Quantum algorithm package based on Cqlib
Author-email: China Telecom Quantum Group Quantum Computing Team <tianyan@chinatelecom.cn>
License-Expression: Apache-2.0
Project-URL: Homepage, https://qc.zdxlz.com/
Project-URL: Documentation, https://qc.zdxlz.com/learn/#/resource/informationSpace
Project-URL: Repository, https://gitee.com/cq-lib/cqlib-algorithm
Project-URL: Issues, https://gitee.com/cq-lib/cqlib-algorithm/issues
Keywords: cqlib,cqlib algorithms,quantum circuit,quantum computing,quantum programming language,quantum,quantum algorithms
Classifier: Environment :: Console
Classifier: Operating System :: MacOS
Classifier: Operating System :: Microsoft :: Windows
Classifier: Operating System :: POSIX :: Linux
Classifier: Programming Language :: Python :: 3 :: Only
Classifier: Programming Language :: Python :: 3.10
Classifier: Programming Language :: Python :: 3.11
Classifier: Programming Language :: Python :: 3.12
Classifier: Programming Language :: Python :: 3.13
Classifier: Programming Language :: Python :: 3.14
Classifier: Intended Audience :: Science/Research
Classifier: Topic :: Software Development :: Libraries
Requires-Python: >=3.10
License-File: LICENSE
Requires-Dist: cqlib>=1.3.5
Requires-Dist: matplotlib>=3.7.5
Requires-Dist: networkx>=3.0
Requires-Dist: numpy>=2.1.2
Requires-Dist: scipy>=1.10.0
Dynamic: license-file
